qbuspy/__init__.py
qbuspy/exceptions.py
qbuspy/interface.py
qbuspy-0.1.0.dist-info/LICENSE
qbuspy-0.1.0.dist-info/WHEEL
qbuspy-0.1.0.dist-info/METADATA
qbuspy-0.1.0.dist-info/RECORD
