Metadata-Version: 2.1
Name: qbuspy
Version: 0.1.0
Summary: Qbuspy is the python package for easy interfacing with the Qbus home automation system.
Home-page: https://github.com/vlaminckaxel/qbuspy
License: MIT
Keywords: qbus
Author: vlaminckaxel
Author-email: axel.vlaminck@gmail.com
Requires-Python: >=3.9,<4.0
Classifier: License :: OSI Approved :: MIT License
Classifier: Programming Language :: Python :: 3
Classifier: Programming Language :: Python :: 3.10
Classifier: Programming Language :: Python :: 3.9
Requires-Dist: requests (>=2.27.1,<3.0.0)
Project-URL: Documentation, https://github.com/vlaminckaxel/qbuspy
Project-URL: Repository, https://github.com/vlaminckaxel/qbuspy
